octastore/__config__.py
octastore/__init__.py
octastore/cli.py
octastore/config.py
octastore/dbf.py
octastore/example.py
octastore/octaFile.py
octastore/octacluster.py
octastore/octastore.py
octastore-0.3.7.dist-info/licenses/LICENSE
octastore-0.3.7.dist-info/METADATA
octastore-0.3.7.dist-info/WHEEL
octastore-0.3.7.dist-info/entry_points.txt
octastore-0.3.7.dist-info/top_level.txt
octastore-0.3.7.dist-info/RECORD
