Metadata-Version: 2.4
Name: octastore
Version: 0.3.7
Summary: OctaStore is a custom database system built with Python and powered by GitHub, treating GitHub repositories as databases. It features encryption using the cryptography library, ensuring data security.
Home-page: https://github.com/TaireruLLC/octastore
Author: Taireru LLC
Author-email: tairerullc@gmail.com
License: MIT
Classifier: Programming Language :: Python :: 3
Classifier: Operating System :: OS Independent
Requires-Python: >=3.6
License-File: LICENSE
Requires-Dist: requests
Requires-Dist: cryptography
Requires-Dist: altcolor>=0.0.5
Requires-Dist: moviepy
Requires-Dist: fancyutil>=0.0.4
Requires-Dist: numpy
Requires-Dist: opencv-python
Requires-Dist: pyaudio
Requires-Dist: wave
Requires-Dist: jsonpickle
Dynamic: author
Dynamic: author-email
Dynamic: classifier
Dynamic: description
Dynamic: description-content-type
Dynamic: home-page
Dynamic: license
Dynamic: license-file
Dynamic: requires-dist
Dynamic: requires-python
Dynamic: summary
